hypt/__init__.py
hypt/distributions.py
hypt/dynamic.py
hypt/linesearch.py
hypt/protocol.py
hypt/random.py
hypt/static.py
hypt/utils.py
hypt-0.2.0.dist-info/licenses/LICENSE
hypt-0.2.0.dist-info/METADATA
hypt-0.2.0.dist-info/WHEEL
hypt-0.2.0.dist-info/top_level.txt
hypt-0.2.0.dist-info/RECORD
