Metadata-Version: 2.4
Name: hypt
Version: 0.2.0
Summary: Simple hyperparameter tuning in Python
Author-email: João Bravo <ajoo@outlook.pt>
License-Expression: MIT
Project-URL: Repository, https://github.com/Ajoo/hypt
Keywords: hyperparameter tuning,optimization
Requires-Python: >=3.10
License-File: LICENSE
Requires-Dist: numpy
Dynamic: license-file
